{
    "non-spinning eccentric": {
        "total_count": 74,
        "simulations": [
            "GT0371",
            "GT0372",
            "GT0376",
            "GT0378",
            "GT0379",
            "GT0380",
            "GT0565",
            "GT0577",
            "GT0601",
            "GT0604",
            "GT0615",
            "GT0617",
            "GT0618",
            "GT0621",
            "GT0622",
            "GT0656",
            "GT0717",
            "GT0730",
            "GT0777",
            "GT0778",
            "GT0780",
            "GT0791",
            "GT0795",
            "GT0797",
            "GT0798",
            "GT0818",
            "GT0824",
            "GT0905",
            "GT0906",
            "MAYA0922",
            "MAYA0923",
            "MAYA0924",
            "MAYA0925",
            "MAYA0926",
            "MAYA0927",
            "MAYA0928",
            "MAYA0929",
            "MAYA0930",
            "MAYA0931",
            "MAYA0932",
            "MAYA0933",
            "MAYA0934",
            "MAYA0935",
            "MAYA0936",
            "MAYA0949",
            "MAYA0950",
            "MAYA0951",
            "MAYA0952",
            "MAYA0953",
            "MAYA0954",
            "MAYA0955",
            "MAYA0956",
            "MAYA0957",
            "MAYA0958",
            "MAYA0971",
            "MAYA0972",
            "MAYA0973",
            "MAYA0974",
            "MAYA0975",
            "MAYA0976",
            "MAYA0977",
            "MAYA0978",
            "MAYA0979",
            "MAYA0980",
            "MAYA0992",
            "MAYA0993",
            "MAYA0994",
            "MAYA0995",
            "MAYA0996",
            "MAYA0997",
            "MAYA0998",
            "MAYA0999",
            "MAYA1000",
            "MAYA1001"
        ]
    },
    "non-spinning non-eccentric": {
        "total_count": 34,
        "simulations": [
            "GT0282",
            "GT0283",
            "GT0370",
            "GT0374",
            "GT0446",
            "GT0448",
            "GT0453",
            "GT0454",
            "GT0477",
            "GT0568",
            "GT0650",
            "GT0651",
            "GT0652",
            "GT0653",
            "GT0654",
            "GT0727",
            "GT0738",
            "GT0748",
            "GT0757",
            "GT0758",
            "GT0759",
            "GT0760",
            "GT0761",
            "GT0898",
            "MAYA0948",
            "MAYA0970",
            "MAYA1005",
            "MAYA1007",
            "MAYA1008",
            "MAYA1010",
            "MAYA1015",
            "MAYA1032",
            "MAYA1039",
            "MAYA1040"
        ]
    },
    "aligned-spin eccentric": {
        "total_count": 117,
        "simulations": [
            "GT0358",
            "GT0389",
            "GT0392",
            "GT0406",
            "GT0407",
            "GT0411",
            "GT0413",
            "GT0414",
            "GT0422",
            "GT0424",
            "GT0471",
            "GT0472",
            "GT0475",
            "GT0476",
            "GT0480",
            "GT0543",
            "GT0545",
            "GT0547",
            "GT0548",
            "GT0549",
            "GT0554",
            "GT0558",
            "GT0564",
            "GT0566",
            "GT0570",
            "GT0573",
            "GT0578",
            "GT0579",
            "GT0580",
            "GT0582",
            "GT0587",
            "GT0588",
            "GT0590",
            "GT0596",
            "GT0599",
            "GT0600",
            "GT0602",
            "GT0603",
            "GT0608",
            "GT0610",
            "GT0611",
            "GT0612",
            "GT0676",
            "GT0688",
            "GT0740",
            "GT0765",
            "GT0768",
            "GT0769",
            "GT0770",
            "GT0771",
            "GT0779",
            "GT0830",
            "GT0835",
            "GT0836",
            "GT0837",
            "GT0838",
            "GT0839",
            "GT0840",
            "GT0841",
            "GT0845",
            "GT0846",
            "GT0890",
            "MAYA0907",
            "MAYA0908",
            "MAYA0912",
            "MAYA0913",
            "MAYA0914",
            "MAYA0915",
            "MAYA0916",
            "MAYA0917",
            "MAYA0918",
            "MAYA0919",
            "MAYA0920",
            "MAYA0921",
            "MAYA0938",
            "MAYA0939",
            "MAYA0940",
            "MAYA0941",
            "MAYA0942",
            "MAYA0943",
            "MAYA0944",
            "MAYA0945",
            "MAYA0946",
            "MAYA0947",
            "MAYA0960",
            "MAYA0961",
            "MAYA0962",
            "MAYA0963",
            "MAYA0964",
            "MAYA0965",
            "MAYA0966",
            "MAYA0967",
            "MAYA0968",
            "MAYA0969",
            "MAYA0982",
            "MAYA0983",
            "MAYA0984",
            "MAYA0985",
            "MAYA0986",
            "MAYA0987",
            "MAYA0988",
            "MAYA0989",
            "MAYA0990",
            "MAYA0991",
            "MAYA1004",
            "MAYA1006",
            "MAYA1009",
            "MAYA1012",
            "MAYA1013",
            "MAYA1014",
            "MAYA1019",
            "MAYA1027",
            "MAYA1031",
            "MAYA1034",
            "MAYA1037",
            "MAYA1038",
            "MAYA1041"
        ]
    },
    "aligned-spin non-eccentric": {
        "total_count": 40,
        "simulations": [
            "GT0355",
            "GT0356",
            "GT0357",
            "GT0405",
            "GT0415",
            "GT0420",
            "GT0479",
            "GT0546",
            "GT0551",
            "GT0555",
            "GT0574",
            "GT0583",
            "GT0584",
            "GT0598",
            "GT0842",
            "GT0843",
            "GT0844",
            "MAYA0909",
            "MAYA0937",
            "MAYA0959",
            "MAYA0981",
            "MAYA1002",
            "MAYA1003",
            "MAYA1011",
            "MAYA1016",
            "MAYA1017",
            "MAYA1018",
            "MAYA1020",
            "MAYA1021",
            "MAYA1022",
            "MAYA1023",
            "MAYA1024",
            "MAYA1025",
            "MAYA1026",
            "MAYA1028",
            "MAYA1029",
            "MAYA1030",
            "MAYA1033",
            "MAYA1035",
            "MAYA1036"
        ]
    },
    "precessing-spin eccentric": {
        "total_count": 303,
        "simulations": [
            "GT0003",
            "GT0004",
            "GT0005",
            "GT0006",
            "GT0010",
            "GT0011",
            "GT0012",
            "GT0013",
            "GT0014",
            "GT0015",
            "GT0203",
            "GT0204",
            "GT0205",
            "GT0206",
            "GT0207",
            "GT0208",
            "GT0209",
            "GT0227",
            "GT0229",
            "GT0261",
            "GT0262",
            "GT0264",
            "GT0265",
            "GT0267",
            "GT0275",
            "GT0277",
            "GT0278",
            "GT0280",
            "GT0281",
            "GT0286",
            "GT0287",
            "GT0304",
            "GT0308",
            "GT0311",
            "GT0314",
            "GT0382",
            "GT0384",
            "GT0390",
            "GT0391",
            "GT0393",
            "GT0395",
            "GT0396",
            "GT0397",
            "GT0398",
            "GT0400",
            "GT0401",
            "GT0428",
            "GT0430",
            "GT0431",
            "GT0432",
            "GT0433",
            "GT0435",
            "GT0437",
            "GT0438",
            "GT0440",
            "GT0441",
            "GT0443",
            "GT0455",
            "GT0456",
            "GT0457",
            "GT0458",
            "GT0459",
            "GT0460",
            "GT0461",
            "GT0462",
            "GT0463",
            "GT0464",
            "GT0465",
            "GT0466",
            "GT0467",
            "GT0468",
            "GT0469",
            "GT0470",
            "GT0478",
            "GT0482",
            "GT0483",
            "GT0484",
            "GT0485",
            "GT0486",
            "GT0487",
            "GT0489",
            "GT0490",
            "GT0491",
            "GT0492",
            "GT0493",
            "GT0500",
            "GT0501",
            "GT0502",
            "GT0503",
            "GT0504",
            "GT0505",
            "GT0506",
            "GT0507",
            "GT0508",
            "GT0509",
            "GT0510",
            "GT0511",
            "GT0512",
            "GT0520",
            "GT0521",
            "GT0522",
            "GT0523",
            "GT0526",
            "GT0527",
            "GT0528",
            "GT0529",
            "GT0530",
            "GT0532",
            "GT0533",
            "GT0534",
            "GT0535",
            "GT0536",
            "GT0539",
            "GT0540",
            "GT0541",
            "GT0542",
            "GT0550",
            "GT0556",
            "GT0557",
            "GT0560",
            "GT0567",
            "GT0605",
            "GT0606",
            "GT0607",
            "GT0609",
            "GT0613",
            "GT0626",
            "GT0628",
            "GT0630",
            "GT0633",
            "GT0634",
            "GT0635",
            "GT0636",
            "GT0637",
            "GT0638",
            "GT0641",
            "GT0642",
            "GT0644",
            "GT0645",
            "GT0646",
            "GT0647",
            "GT0648",
            "GT0649",
            "GT0657",
            "GT0659",
            "GT0660",
            "GT0661",
            "GT0662",
            "GT0665",
            "GT0666",
            "GT0667",
            "GT0668",
            "GT0669",
            "GT0670",
            "GT0671",
            "GT0672",
            "GT0673",
            "GT0674",
            "GT0677",
            "GT0678",
            "GT0679",
            "GT0680",
            "GT0681",
            "GT0682",
            "GT0683",
            "GT0684",
            "GT0685",
            "GT0686",
            "GT0689",
            "GT0690",
            "GT0691",
            "GT0692",
            "GT0694",
            "GT0695",
            "GT0696",
            "GT0698",
            "GT0699",
            "GT0702",
            "GT0703",
            "GT0706",
            "GT0707",
            "GT0709",
            "GT0710",
            "GT0712",
            "GT0714",
            "GT0715",
            "GT0718",
            "GT0720",
            "GT0721",
            "GT0722",
            "GT0723",
            "GT0724",
            "GT0725",
            "GT0726",
            "GT0728",
            "GT0729",
            "GT0732",
            "GT0733",
            "GT0734",
            "GT0735",
            "GT0739",
            "GT0741",
            "GT0742",
            "GT0743",
            "GT0744",
            "GT0745",
            "GT0746",
            "GT0747",
            "GT0749",
            "GT0750",
            "GT0754",
            "GT0756",
            "GT0762",
            "GT0763",
            "GT0764",
            "GT0766",
            "GT0767",
            "GT0781",
            "GT0787",
            "GT0792",
            "GT0794",
            "GT0796",
            "GT0799",
            "GT0800",
            "GT0801",
            "GT0803",
            "GT0805",
            "GT0807",
            "GT0808",
            "GT0809",
            "GT0810",
            "GT0825",
            "GT0833",
            "GT0834",
            "GT0847",
            "GT0848",
            "GT0851",
            "GT0852",
            "GT0853",
            "GT0854",
            "GT0856",
            "GT0857",
            "GT0858",
            "GT0859",
            "GT0861",
            "GT0862",
            "GT0863",
            "GT0864",
            "GT0865",
            "GT0867",
            "GT0868",
            "GT0869",
            "GT0870",
            "GT0871",
            "GT0872",
            "GT0873",
            "GT0874",
            "GT0875",
            "GT0876",
            "GT0877",
            "GT0878",
            "GT0879",
            "GT0880",
            "GT0881",
            "GT0882",
            "GT0883",
            "GT0884",
            "GT0885",
            "GT0886",
            "GT0887",
            "GT0888",
            "GT0889",
            "GT0891",
            "GT0893",
            "GT0894",
            "GT0895",
            "GT0896",
            "GT0897",
            "GT0900",
            "MAYA0910",
            "MAYA0911",
            "MAYA1043",
            "MAYA1044",
            "MAYA1045",
            "MAYA1046",
            "MAYA1047",
            "MAYA1048",
            "MAYA1049",
            "MAYA1050",
            "MAYA1052",
            "MAYA1055",
            "MAYA1056",
            "MAYA1058",
            "MAYA1059",
            "MAYA1062",
            "MAYA1068",
            "MAYA1074",
            "MAYA1075",
            "MAYA1079",
            "MAYA1083",
            "MAYA1084",
            "MAYA1086",
            "MAYA1087"
        ]
    },
    "precessing-spin non-eccentric": {
        "total_count": 67,
        "simulations": [
            "GT0001",
            "GT0002",
            "GT0007",
            "GT0008",
            "GT0009",
            "GT0016",
            "GT0255",
            "GT0256",
            "GT0258",
            "GT0259",
            "GT0272",
            "GT0284",
            "GT0285",
            "GT0385",
            "GT0388",
            "GT0434",
            "GT0513",
            "GT0514",
            "GT0515",
            "GT0516",
            "GT0517",
            "GT0518",
            "GT0524",
            "GT0525",
            "GT0537",
            "GT0538",
            "GT0544",
            "GT0629",
            "GT0632",
            "GT0639",
            "GT0640",
            "GT0643",
            "GT0663",
            "GT0664",
            "GT0693",
            "GT0697",
            "GT0701",
            "GT0704",
            "GT0705",
            "GT0708",
            "GT0713",
            "GT0860",
            "GT0866",
            "MAYA1042",
            "MAYA1051",
            "MAYA1053",
            "MAYA1054",
            "MAYA1057",
            "MAYA1060",
            "MAYA1061",
            "MAYA1063",
            "MAYA1064",
            "MAYA1065",
            "MAYA1066",
            "MAYA1067",
            "MAYA1069",
            "MAYA1070",
            "MAYA1071",
            "MAYA1072",
            "MAYA1073",
            "MAYA1076",
            "MAYA1077",
            "MAYA1078",
            "MAYA1080",
            "MAYA1081",
            "MAYA1082",
            "MAYA1085"
        ]
    }
}